dhcpkit_looking_glass/__init__.py
dhcpkit_looking_glass/admin.py
dhcpkit_looking_glass/app_settings.py
dhcpkit_looking_glass/apps.py
dhcpkit_looking_glass/filters.py
dhcpkit_looking_glass/models.py
dhcpkit_looking_glass/tests.py
dhcpkit_looking_glass/utils.py
dhcpkit_looking_glass/views.py
dhcpkit_looking_glass/management/__init__.py
dhcpkit_looking_glass/management/commands/__init__.py
dhcpkit_looking_glass/management/commands/process_kafka.py
dhcpkit_looking_glass/migrations/0001_initial.py
dhcpkit_looking_glass/migrations/0002_auto_20151110_0017.py
dhcpkit_looking_glass/migrations/0003_rename_client_to_transaction.py
dhcpkit_looking_glass/migrations/0004_add_client_server.py
dhcpkit_looking_glass/migrations/0005_move_data.py
dhcpkit_looking_glass/migrations/0006_remove_old_fields.py
dhcpkit_looking_glass/migrations/0007_fix_fields.py
dhcpkit_looking_glass/migrations/__init__.py
dhcpkit_looking_glass-0.9.2.dist-info/DESCRIPTION.rst
dhcpkit_looking_glass-0.9.2.dist-info/METADATA
dhcpkit_looking_glass-0.9.2.dist-info/RECORD
dhcpkit_looking_glass-0.9.2.dist-info/WHEEL
dhcpkit_looking_glass-0.9.2.dist-info/metadata.json
dhcpkit_looking_glass-0.9.2.dist-info/top_level.txt
